stringpairfinder/__init__.py
stringpairfinder/process.py
stringpairfinder-2.0.1.dist-info/LICENSE
stringpairfinder-2.0.1.dist-info/METADATA
stringpairfinder-2.0.1.dist-info/WHEEL
stringpairfinder-2.0.1.dist-info/top_level.txt
stringpairfinder-2.0.1.dist-info/RECORD
