Metadata-Version: 2.2
Name: stringpairfinder
Version: 2.0.1
Summary: Package designed to match strings by similarity
Home-page: https://github.com/AntoinePinto/stringpairfinder
Author: Antoine PINTO
Author-email: antoine.pinto1@outlook.fr
License: MIT
Project-URL: Source Code, https://github.com/AntoinePinto/stringpairfinder
Keywords: string,string matching,algorithm,similarity
Requires-Python: >=3.7
License-File: LICENSE
Requires-Dist: numpy>=1.21.6
Dynamic: author
Dynamic: author-email
Dynamic: description
Dynamic: description-content-type
Dynamic: home-page
Dynamic: keywords
Dynamic: license
Dynamic: project-url
Dynamic: requires-dist
Dynamic: requires-python
Dynamic: summary
